hars/__init__.py
hars/har.py
hars-0.4.dist-info/licenses/LICENSE
hars-0.4.dist-info/METADATA
hars-0.4.dist-info/WHEEL
hars-0.4.dist-info/top_level.txt
hars-0.4.dist-info/RECORD
