Metadata-Version: 2.4
Name: hars
Version: 0.4
Summary: some tools for har
Author-email: yjk <mr.yjk@foxmail.com>
License:                                  Apache License
Project-URL: Homepage, https://github.com/yjk114514/har
Requires-Python: >=3.7
License-File: LICENSE
Requires-Dist: requests
Dynamic: license-file
